ragl/__init__.py
ragl/config.py
ragl/constants.py
ragl/exceptions.py
ragl/factory.py
ragl/manager.py
ragl/protocols.py
ragl/py.typed
ragl/ragstore.py
ragl/schema.py
ragl/textunit.py
ragl/tokenizer.py
ragl/embed/__init__.py
ragl/embed/sentencetransformer.py
ragl/store/__init__.py
ragl/store/redis.py
ragl-0.10.1.dist-info/licenses/LICENSE
tests/functional/ragl/test_config.py
tests/functional/ragl/test_factory.py
tests/functional/ragl/test_manager.py
tests/functional/ragl/test_ragstore.py
tests/functional/ragl/test_schema.py
tests/functional/ragl/test_textunit.py
tests/functional/ragl/test_tokenizer.py
tests/functional/ragl/embed/test_sentencetransformer.py
tests/functional/ragl/store/test_redis.py
tests/integration/sentencetransformer_redis.py
ragl-0.10.1.dist-info/METADATA
ragl-0.10.1.dist-info/WHEEL
ragl-0.10.1.dist-info/top_level.txt
ragl-0.10.1.dist-info/RECORD
